[{"_path":"/dokos/lieu/parametres-lieu","title":"Paramètres du lieu","description":"Les paramètres du lieu dans Dokos sont conçus pour faciliter la gestion des espaces et des ressources, tels que les Tiers Lieux, les espaces de coworking, les ateliers, les salles de réunion. Ils permettent de personnaliser et d'optimiser la gestion des réservations et des activités associées à chaque lieu."},{"_path":"/dokos/lieu/reservations/reservations-articles","title":"Réservations de ressources","description":"les ressources réservables sont configurées pour informer et publier des ressources sur le site, tandis que les réservations d'articles permettent la gestion des réservations effectives de ces ressources par les utilisateurs."}]