{"_path":"/dokos/actifs/demarrer","_dir":"actifs","_draft":false,"_partial":false,"_locale":"fr","title":"Premiers pas avec les actifs","description":"","body":{"type":"root","children":[{"type":"element","tag":"mermaid","props":{},"children":[{"type":"text","value":"\ngraph LR;\n\ti0(Catégorie d'actifs)-->i1(Article);\n\ti1-->i2(Facture/Reçu d'achat);\n  i2-->i3(Actif);\n"}]},{"type":"element","tag":"p","props":{},"children":[{"type":"text","value":"Cet exemple est basé sur la configuration de démonstration de Dokos disponible à l'adresse "},{"type":"element","tag":"a","props":{"href":"https://demo.dokos.cloud","rel":["nofollow"]},"children":[{"type":"text","value":"https://demo.dokos.cloud"}]}]},{"type":"element","tag":"h1","props":{"id":"cas-dusage"},"children":[{"type":"text","value":"Cas d'usage"}]},{"type":"element","tag":"p","props":{},"children":[{"type":"text","value":"Notre société Dokostration a acquis un ordinateur pour pouvoir utiliser le logiciel Dokos . Elle doit comptabiliser l'achat de ce logiciel ainsi que prévoir un tableau d'amortissement afin d'amortir cet achat sur 3 ans."}]},{"type":"element","tag":"h3","props":{"id":"_1-création-dune-nouvelle-catégorie-dactifs"},"children":[{"type":"text","value":"1. Création d'une nouvelle catégorie d'actifs"}]},{"type":"element","tag":"p","props":{},"children":[{"type":"text","value":"L'élément permettant de lier l'amortissement de notre actif et sa facturation est l'"},{"type":"element","tag":"strong","props":{},"children":[{"type":"text","value":"Article"}]},{"type":"text","value":". Cet article sera lié à une catégorie d'actif définissant le paramétrage spécifique applicable à notre actif."}]},{"type":"element","tag":"p","props":{},"children":[{"type":"text","value":"Nous allons donc créer une nouvelle catégorie d'actifs appelée "},{"type":"element","tag":"strong","props":{},"children":[{"type":"text","value":"Matériel Informatique"}]},{"type":"text","value":".\nCette catégorie d'actifs ne permettra pas la comptabilisation des immobilisations en cours."}]},{"type":"element","tag":"p","props":{},"children":[{"type":"text","value":"Voici les paramètres que nous attribuons à cette catégorie. Ces paramètres seront repris lors de la création de notre actif."}]},{"type":"text","value":"\n\n\n\n\n\n\n\n\n\n\n\n\n\n\n\n\n\n\n\n"},{"type":"element","tag":"table","props":{},"children":[{"type":"element","tag":"thead","props":{},"children":[{"type":"element","tag":"tr","props":{},"children":[{"type":"element","tag":"th","props":{},"children":[{"type":"text","value":"Livre comptable"}]},{"type":"element","tag":"th","props":{},"children":[{"type":"text","value":"Méthode d'amortissement"}]},{"type":"element","tag":"th","props":{},"children":[{"type":"text","value":"Nombre total d'amortissements"}]},{"type":"element","tag":"th","props":{},"children":[{"type":"text","value":"Fréquence d'amortissement"}]},{"type":"element","tag":"th","props":{},"children":[{"type":"text","value":"Date de début de l'amortissement"}]}]}]},{"type":"element","tag":"tbody","props":{},"children":[{"type":"element","tag":"tr","props":{},"children":[{"type":"element","tag":"td","props":{},"children":[]},{"type":"element","tag":"td","props":{},"children":[{"type":"text","value":"Linéaire au prorata (360 jours)"}]},{"type":"element","tag":"td","props":{},"children":[{"type":"text","value":"4"}]},{"type":"element","tag":"td","props":{},"children":[{"type":"text","value":"12"}]},{"type":"element","tag":"td","props":{},"children":[]}]}]}]},{"type":"element","tag":"br","props":{},"children":[]},{"type":"text","value":"\n\n\n\n\n\n\n\n\n\n\n\n\n\n\n\n\n\n\n\n"},{"type":"element","tag":"table","props":{},"children":[{"type":"element","tag":"thead","props":{},"children":[{"type":"element","tag":"tr","props":{},"children":[{"type":"element","tag":"th","props":{},"children":[{"type":"text","value":"Société"}]},{"type":"element","tag":"th","props":{},"children":[{"type":"text","value":"Compte d'actif immobilisé"}]},{"type":"element","tag":"th","props":{},"children":[{"type":"text","value":"Compte d'amortissement cumulé"}]},{"type":"element","tag":"th","props":{},"children":[{"type":"text","value":"Compte de dotations aux amortissement"}]},{"type":"element","tag":"th","props":{},"children":[{"type":"text","value":"Compte d'immobilisation en cours"}]}]}]},{"type":"element","tag":"tbody","props":{},"children":[{"type":"element","tag":"tr","props":{},"children":[{"type":"element","tag":"td","props":{},"children":[{"type":"text","value":"Dokostration"}]},{"type":"element","tag":"td","props":{},"children":[{"type":"text","value":"218  - Autres immobilisations corporelles - D"}]},{"type":"element","tag":"td","props":{},"children":[{"type":"text","value":"281  - Amortissements des immobilisations corporelles - D"}]},{"type":"element","tag":"td","props":{},"children":[{"type":"text","value":"681  - Dotations aux amortissements, dépréciations et provisions - D"}]},{"type":"element","tag":"td","props":{},"children":[]}]}]}]},{"type":"element","tag":"h3","props":{"id":"_2-création-dun-nouvel-article"},"children":[{"type":"text","value":"2. Création d'un nouvel article"}]},{"type":"element","tag":"p","props":{},"children":[{"type":"text","value":"Nous allons donc créer un nouvel article "},{"type":"element","tag":"em","props":{},"children":[{"type":"text","value":"Ordinateur"}]},{"type":"text","value":" et cocher la case "},{"type":"element","tag":"strong","props":{},"children":[{"type":"text","value":"Est une immobilisation"}]},{"type":"text","value":"."}]},{"type":"element","tag":"p","props":{},"children":[{"type":"text","value":"Nous allons également associer cet article à la catégorie d'actifs "},{"type":"element","tag":"strong","props":{},"children":[{"type":"text","value":"Matériel Informatique"}]},{"type":"text","value":"."}]},{"type":"element","tag":"h3","props":{"id":"_3-création-de-la-facture-dachat-correspondante"},"children":[{"type":"text","value":"3. Création de la facture d'achat correspondante"}]},{"type":"element","tag":"p","props":{},"children":[{"type":"text","value":"Nous créons ensuite une facture d'achat pour notre ordinateur en sélectionnant l'article "},{"type":"element","tag":"strong","props":{},"children":[{"type":"text","value":"Ordinateur"}]},{"type":"text","value":"."}]},{"type":"element","tag":"p","props":{},"children":[{"type":"text","value":"Vous pouvez constater que le compte comptable associé à la ligne d'article "},{"type":"element","tag":"strong","props":{},"children":[{"type":"text","value":"Ordinateur"}]},{"type":"text","value":" n'est pas un compte de charges, mais le compte d'actif immobilisé configuré dans notre catégorie d'actif."}]},{"type":"element","tag":"p","props":{},"children":[{"type":"text","value":"Faites bien attention que la TVA soit associée à l'option "},{"type":"element","tag":"em","props":{},"children":[{"type":"text","value":"Tenir compte des taxes et frais pour"}]},{"type":"text","value":" "},{"type":"element","tag":"strong","props":{},"children":[{"type":"text","value":"Total"}]},{"type":"text","value":"."}]},{"type":"element","tag":"p","props":{},"children":[{"type":"text","value":"Si la TVA n'est pas récupérable, mettez le montant TTC dans la ligne d'article "},{"type":"element","tag":"strong","props":{},"children":[{"type":"text","value":"Ordinateur"}]},{"type":"text","value":"."}]},{"type":"element","tag":"p","props":{},"children":[{"type":"text","value":"Validez la facture."}]},{"type":"element","tag":"h3","props":{"id":"_4-création-de-lactif-et-génération-du-tableau-damortissement"},"children":[{"type":"text","value":"4. Création de l'actif et génération du tableau d'amortissement"}]},{"type":"element","tag":"p","props":{},"children":[{"type":"text","value":"Dans le module "},{"type":"element","tag":"strong","props":{},"children":[{"type":"text","value":"Actifs"}]},{"type":"text","value":", nous créons ensuite un nouvel actif, lui donnons un nom et le lions au code d'article "},{"type":"element","tag":"strong","props":{},"children":[{"type":"text","value":"Ordinateur"}]},{"type":"text","value":"."}]},{"type":"element","tag":"p","props":{},"children":[{"type":"text","value":"Tout en bas du document, dans la section Autres détails, nous sélectionnons votre facture d'achat."}]},{"type":"element","tag":"p","props":{},"children":[{"type":"text","value":"Il ne reste plus qu'à sélectionner la localisation de cet actif, puis à cocher la case "},{"type":"element","tag":"strong","props":{},"children":[{"type":"text","value":"Calculer la dépréciation"}]},{"type":"text","value":" et à mettre la date de mise en service de notre actif."}]},{"type":"element","tag":"p","props":{},"children":[{"type":"text","value":"Après enregistrement, le système a calculé le tableau d'amortissement. Il ne nous reste plus qu'à valider."}]}],"toc":{"title":"","searchDepth":2,"depth":2,"links":[{"id":"_1-création-dune-nouvelle-catégorie-dactifs","depth":3,"text":"1. Création d'une nouvelle catégorie d'actifs"},{"id":"_2-création-dun-nouvel-article","depth":3,"text":"2. Création d'un nouvel article"},{"id":"_3-création-de-la-facture-dachat-correspondante","depth":3,"text":"3. Création de la facture d'achat correspondante"},{"id":"_4-création-de-lactif-et-génération-du-tableau-damortissement","depth":3,"text":"4. Création de l'actif et génération du tableau d'amortissement"}]}},"_type":"markdown","_id":"content:1.dokos:3.actifs:1.demarrer.md","_source":"content","_file":"1.dokos/3.actifs/1.demarrer.md","_extension":"md"}