{"_path":"/dodock/fonctionnalites/personnalisations/paquets","_dir":"personnalisations","_draft":false,"_partial":false,"_locale":"fr","title":"Paquets","description":"Les paquets sont des fichiers permettant de transporter des documents entre différents sites Dokos tout en maintenant un système de versioning.","body":{"type":"root","children":[{"type":"element","tag":"p","props":{},"children":[{"type":"text","value":"Les paquets sont des mécanismes de transport d'éléments personnalisés entre sites Dokos."},{"type":"element","tag":"br","props":{},"children":[]},{"type":"text","value":"\nOn peut les voir comme des applications légères ou des plugins contenant un ou plusieurs modules et des documents associés"}]},{"type":"element","tag":"h2","props":{"id":"concevoir-un-paquet"},"children":[{"type":"text","value":"Concevoir un paquet"}]},{"type":"element","tag":"p","props":{},"children":[{"type":"text","value":"Pour créer un paquet, il faut commencer par créer les éléments qui composeront ce paquet."},{"type":"element","tag":"br","props":{},"children":[]},{"type":"text","value":"\nL'idéal est de créer un "},{"type":"element","tag":"strong","props":{},"children":[{"type":"text","value":"Module"}]},{"type":"text","value":", puis des documents associés comme:"}]},{"type":"element","tag":"ul","props":{},"children":[{"type":"element","tag":"li","props":{},"children":[{"type":"text","value":"Des types de document"}]},{"type":"element","tag":"li","props":{},"children":[{"type":"text","value":"Des formulaires web"}]},{"type":"element","tag":"li","props":{},"children":[{"type":"text","value":"Des scripts clients/serveur"}]},{"type":"element","tag":"li","props":{},"children":[{"type":"text","value":"Des pages web"}]},{"type":"element","tag":"li","props":{},"children":[{"type":"text","value":"etc..."}]}]},{"type":"element","tag":"p","props":{},"children":[{"type":"text","value":"Associez bien tous les documents créé au module qui sera exporté dans votre paquet."}]},{"type":"element","tag":"h2","props":{"id":"génerer-un-paquet"},"children":[{"type":"text","value":"Génerer un paquet"}]},{"type":"element","tag":"p","props":{},"children":[{"type":"text","value":"Une fois tous les éléments composant votre paquet créés, allez dans le menu "},{"type":"element","tag":"strong","props":{},"children":[{"type":"text","value":"Paquet"}]},{"type":"text","value":" ("},{"type":"element","tag":"strong","props":{},"children":[{"type":"text","value":"Administration > Personnalisations"}]},{"type":"text","value":") et créez un nouveau paquet."},{"type":"element","tag":"br","props":{},"children":[]},{"type":"text","value":"\nDonnez lui un nom et une licence."}]},{"type":"element","tag":"p","props":{},"children":[{"type":"text","value":"Ouvrez le module créé plus tôt et associez le avec ce paquet."}]},{"type":"element","tag":"h2","props":{"id":"publier-un-paquet"},"children":[{"type":"text","value":"Publier un paquet"}]},{"type":"element","tag":"p","props":{},"children":[{"type":"text","value":"Depuis votre paquet, cliquez sur "},{"type":"element","tag":"strong","props":{},"children":[{"type":"text","value":"Publication du paquet"}]},{"type":"text","value":" et créez une nouvelle publication."},{"type":"element","tag":"br","props":{},"children":[]},{"type":"text","value":"\nDonnez un numéro de version à votre paquet et renseignez les notes associées."},{"type":"element","tag":"br","props":{},"children":[]},{"type":"text","value":"\nQuand votre paquet est prêt à être publié, cochez la case "},{"type":"element","tag":"strong","props":{},"children":[{"type":"text","value":"Publié"}]},{"type":"text","value":"."}]},{"type":"element","tag":"p","props":{},"children":[{"type":"text","value":"Un fichier "},{"type":"element","tag":"strong","props":{},"children":[{"type":"text","value":".gz"}]},{"type":"text","value":" est généré que vous pouvez télécharger: votre paquet est prêt à être importé dans un autre site."}]},{"type":"element","tag":"h2","props":{"id":"importer-un-paquet"},"children":[{"type":"text","value":"Importer un paquet"}]},{"type":"element","tag":"p","props":{},"children":[{"type":"text","value":"Pour importer un paquet, ouvrez l'outil d'"},{"type":"element","tag":"strong","props":{},"children":[{"type":"text","value":"Import de paquet"}]},{"type":"text","value":" disponible dans le menu "},{"type":"element","tag":"strong","props":{},"children":[{"type":"text","value":"Administration > Personnalisations"}]},{"type":"text","value":"."}]},{"type":"element","tag":"p","props":{},"children":[{"type":"text","value":"Créez un nouvel import de paquet, joignez le fichier "},{"type":"element","tag":"em","props":{},"children":[{"type":"text","value":".gz"}]},{"type":"text","value":" contenant votre paquet, cochez la case "},{"type":"element","tag":"strong","props":{},"children":[{"type":"text","value":"Activer"}]},{"type":"text","value":" et enregistrez. 🎉"}]}],"toc":{"title":"","searchDepth":2,"depth":2,"links":[{"id":"concevoir-un-paquet","depth":2,"text":"Concevoir un paquet"},{"id":"génerer-un-paquet","depth":2,"text":"Génerer un paquet"},{"id":"publier-un-paquet","depth":2,"text":"Publier un paquet"},{"id":"importer-un-paquet","depth":2,"text":"Importer un paquet"}]}},"_type":"markdown","_id":"content:3.dodock:13.fonctionnalites:4.personnalisations:13.paquets.md","_source":"content","_file":"3.dodock/13.fonctionnalites/4.personnalisations/13.paquets.md","_extension":"md"}