{"_path":"/dodock/versions/v3.x.x/v3_14_0","_dir":"v3.x.x","_draft":false,"_partial":false,"_locale":"fr","title":"V3.14.0","description":"","body":{"type":"root","children":[{"type":"element","tag":"h1","props":{"id":"v3140"},"children":[{"type":"text","value":"V3.14.0"}]},{"type":"element","tag":"callout","props":{},"children":[{"type":"element","tag":"p","props":{},"children":[{"type":"text","value":"La version 3.14.0 de Dodock est basée sur la version 14 de Frappe"},{"type":"element","tag":"br","props":{},"children":[]},{"type":"text","value":"\nUne grande partie des changements cités ci-dessous ont été développés par l'équipe de Frappe Technologies et les contributeurs aux logiciels de l'éco-système Frappe/ERPNext"},{"type":"element","tag":"br","props":{},"children":[]},{"type":"text","value":"\nLe détail des changements publiés dans Dodock est disponible sur "},{"type":"element","tag":"a","props":{"href":"https://gitlab.com/dokos/dodock/-/releases/v3.14.0","rel":["nofollow"]},"children":[{"type":"text","value":"Gitlab"}]}]}]},{"type":"element","tag":"callout","props":{"color":"amber","icon":"i-heroicons-exclamation-triangle"},"children":[{"type":"element","tag":"p","props":{},"children":[{"type":"text","value":"Cette page n'indique que les nouvelles fonctionnalités les plus importantes pour chaque module."}]}]},{"type":"element","tag":"h3","props":{"id":"fichiers"},"children":[{"type":"text","value":"Fichiers"}]},{"type":"element","tag":"ul","props":{},"children":[{"type":"element","tag":"li","props":{},"children":[{"type":"text","value":"Ajout d'un système de vérouillage des fichiers pour éviter les conflits lors d'écritures simultanées."},{"type":"element","tag":"br","props":{},"children":[]},{"type":"text","value":"\n👉 "},{"type":"element","tag":"a","props":{"href":"https://github.com/frappe/frappe/pull/19133","rel":["nofollow"]},"children":[{"type":"text","value":"Frappe"}]}]}]},{"type":"element","tag":"h3","props":{"id":"insertions-en-masse"},"children":[{"type":"text","value":"Insertions en masse"}]},{"type":"element","tag":"ul","props":{},"children":[{"type":"element","tag":"li","props":{},"children":[{"type":"text","value":"Il est désormais possible d'insérer des documents sous forme d'objets "},{"type":"element","tag":"em","props":{},"children":[{"type":"text","value":"Document"}]},{"type":"text","value":" en masse."},{"type":"element","tag":"br","props":{},"children":[]},{"type":"text","value":"\n👉 "},{"type":"element","tag":"a","props":{"href":"https://github.com/frappe/frappe/pull/15705","rel":["nofollow"]},"children":[{"type":"text","value":"Frappe"}]}]}]},{"type":"element","tag":"h3","props":{"id":"interface-utilisateur"},"children":[{"type":"text","value":"Interface utilisateur"}]},{"type":"element","tag":"ul","props":{},"children":[{"type":"element","tag":"li","props":{},"children":[{"type":"text","value":"Les en-têtes de séparateurs d'onglet sont désormais bloqués en haut de page lors de la navigation."},{"type":"element","tag":"br","props":{},"children":[]},{"type":"text","value":"\n👉 "},{"type":"element","tag":"a","props":{"href":"https://github.com/frappe/frappe/pull/18906","rel":["nofollow"]},"children":[{"type":"text","value":"Frappe"}]}]}]}],"toc":{"title":"","searchDepth":2,"depth":2,"links":[{"id":"fichiers","depth":3,"text":"Fichiers"},{"id":"insertions-en-masse","depth":3,"text":"Insertions en masse"},{"id":"interface-utilisateur","depth":3,"text":"Interface utilisateur"}]}},"_type":"markdown","_id":"content:3.dodock:98.versions:2.v3.x.x:v3_14_0.md","_source":"content","_file":"3.dodock/98.versions/2.v3.x.x/v3_14_0.md","_extension":"md"}